Globalmart_api_ELT/__init__.py
Globalmart_api_ELT/oops.py
api_data_fetching-0.2.dist-info/METADATA
api_data_fetching-0.2.dist-info/WHEEL
api_data_fetching-0.2.dist-info/top_level.txt
api_data_fetching-0.2.dist-info/RECORD
