Metadata-Version: 2.1
Name: api-data-fetching
Version: 0.2
Summary: API package that provides us the method to fetch the data from the API, along with the method to convert that into proper dataframe
Author: Enqurious
Author-email: enqurious@mentorskool.com
License: MIT
Requires-Dist: pandas
Requires-Dist: requests
